machines_cli/__init__.py
machines_cli/config.py
machines_cli/logging.py
machines_cli/main.py
machines_cli/ssh_config.py
machines_cli/api/__init__.py
machines_cli/api/base.py
machines_cli/api/file_systems.py
machines_cli/api/machines.py
machines_cli/api/ssh_keys.py
machines_cli/api/users.py
machines_cli/api/utils.py
machines_cli/commands/__init__.py
machines_cli/commands/auth/__init__.py
machines_cli/commands/auth/add.py
machines_cli/commands/auth/list.py
machines_cli/commands/auth/remove.py
machines_cli/commands/auth/set.py
machines_cli/commands/file_systems/__init__.py
machines_cli/commands/file_systems/create.py
machines_cli/commands/file_systems/destroy.py
machines_cli/commands/file_systems/duplicate.py
machines_cli/commands/file_systems/extend.py
machines_cli/commands/file_systems/list.py
machines_cli/commands/machines/__init__.py
machines_cli/commands/machines/auto_stop.py
machines_cli/commands/machines/connect.py
machines_cli/commands/machines/create.py
machines_cli/commands/machines/destroy.py
machines_cli/commands/machines/get.py
machines_cli/commands/machines/keep_alive.py
machines_cli/commands/machines/list.py
machines_cli/commands/machines/options.py
machines_cli/commands/machines/restart.py
machines_cli/commands/machines/scale.py
machines_cli/commands/ssh/__init__.py
machines_cli/commands/ssh/add.py
machines_cli/commands/ssh/list.py
machines_cli/commands/ssh/remove.py
machines_cli-0.1.0.dist-info/METADATA
machines_cli-0.1.0.dist-info/WHEEL
machines_cli-0.1.0.dist-info/entry_points.txt
machines_cli-0.1.0.dist-info/RECORD
